{
    "[A]": {
        "inbox": [
            {
                "toFaction": "[A]",
                "fromFaction": "[DUNE]",
                "message": "Welcome to DunePBM",
                "time": ""
            },
            {
                "fromFaction": "[B]",
                "toFaction": "[A]",
                "message": "test",
                "time": ": 1491411400"
            },
            {
                "fromFaction": "[B]",
                "toFaction": "[A]",
                "message": "test",
                "time": ": 1491411400"
            },
            {
                "fromFaction": "[B]",
                "toFaction": "[A]",
                "message": "test2",
                "time": "3: 1491411502"
            },
            {
                "fromFaction": "[B]",
                "toFaction": "[A]",
                "message": "test2",
                "time": "3: 1491411502"
            },
            {
                "fromFaction": "[B]",
                "toFaction": "[A]",
                "message": "test3",
                "time": "3: 1491411507"
            },
            {
                "fromFaction": "[B]",
                "toFaction": "[A]",
                "message": "test3",
                "time": "3: 1491411507"
            }
        ],
        "sent": []
    },
    "[B]": {
        "inbox": [
            {
                "toFaction": "[A]",
                "fromFaction": "[DUNE]",
                "message": "Welcome to DunePBM",
                "time": ""
            }
        ],
        "sent": [
            {
                "fromFaction": "[B]",
                "toFaction": "[A]",
                "message": "test",
                "time": ": 1491411400"
            },
            {
                "fromFaction": "[B]",
                "toFaction": "[A]",
                "message": "test2",
                "time": "3: 1491411502"
            },
            {
                "fromFaction": "[B]",
                "toFaction": "[A]",
                "message": "test3",
                "time": "3: 1491411507"
            }
        ]
    },
    "[E]": {
        "inbox": [
            {
                "toFaction": "[A]",
                "fromFaction": "[DUNE]",
                "message": "Welcome to DunePBM",
                "time": ""
            }
        ],
        "sent": []
    },
    "[F]": {
        "inbox": [
            {
                "toFaction": "[A]",
                "fromFaction": "[DUNE]",
                "message": "Welcome to DunePBM",
                "time": ""
            }
        ],
        "sent": []
    },
    "[G]": {
        "inbox": [
            {
                "toFaction": "[A]",
                "fromFaction": "[DUNE]",
                "message": "Welcome to DunePBM",
                "time": ""
            }
        ],
        "sent": []
    },
    "[H]": {
        "inbox": [
            {
                "toFaction": "[A]",
                "fromFaction": "[DUNE]",
                "message": "Welcome to DunePBM",
                "time": ""
            }
        ],
        "sent": []
    }
}